myApp/__init__.py
myApp/fileTree.py
myApp/license_config.json
myApp/main.py
myApp/test_display.py
myApp/data/EULA
myApp/data/LICENSE
radis_app-0.1.20.dist-info/METADATA
radis_app-0.1.20.dist-info/WHEEL
radis_app-0.1.20.dist-info/entry_points.txt
radis_app-0.1.20.dist-info/RECORD
