Metadata-Version: 2.4
Name: radis-app
Version: 0.1.20
Summary: A simple CLI app that prints personal info
Author-email: Radiela Yorgova <you@example.com>
Requires-Python: >=3.8
